osupyparser/__init__.py
osupyparser/const.py
osupyparser/difficulty.py
osupyparser/editor.py
osupyparser/events.py
osupyparser/general.py
osupyparser/hitobject.py
osupyparser/hitobjects.py
osupyparser/metadata.py
osupyparser/osuparser.py
osupyparser/timingpoint.py
osupyparser/timingpoints.py
OsuPyParser-0.2.3.dist-info/LICENSE
OsuPyParser-0.2.3.dist-info/METADATA
OsuPyParser-0.2.3.dist-info/WHEEL
OsuPyParser-0.2.3.dist-info/top_level.txt
OsuPyParser-0.2.3.dist-info/RECORD
