Metadata-Version: 2.1
Name: OsuPyParser
Version: 0.2.3
Summary: A powerful package for parsing .osu extention file
Home-page: https://github.com/lenforiee/osupyparser
Author: Lenforiee
Author-email: lenforiee@misumi.me
License: UNKNOWN
Platform: UNKNOWN
Classifier: Programming Language :: Python :: 3
Classifier: License :: OSI Approved :: MIT License
Classifier: Operating System :: OS Independent
Requires-Python: >=3.6
License-File: LICENSE
